{
  "info": {
    "description": "CherryBBCH72 Dataset - Cherry fruit images captured during fruit development stage (BBCH 72-73)",
    "version": "1.0",
    "year": 2025,
    "contributor": "search engine",
    "source": "augmented",
    "license": {
      "name": "Creative Commons Attribution 4.0 International",
      "url": "https://creativecommons.org/licenses/by/4.0/"
    }
  },
  "images": [
    {
      "id": 5576404192,
      "width": 640,
      "height": 640,
      "file_name": "IMGP8627_33.jpg",
      "size": 44351,
      "format": "JPEG",
      "url": "",
      "hash": "",
      "status": "success"
    }
  ],
  "annotations": [
    {
      "id": 7753975193,
      "image_id": 5576404192,
      "category_id": 7703517192,
      "segmentation": [],
      "area": 1224.0,
      "bbox": [
        232.27136,
        561.0,
        36.0,
        34.0
      ]
    },
    {
      "id": 6254672193,
      "image_id": 5576404192,
      "category_id": 7703517192,
      "segmentation": [],
      "area": 890.9980798976001,
      "bbox": [
        275.27392000000003,
        517.0,
        26.99968,
        33.00032
      ]
    },
    {
      "id": 8670381193,
      "image_id": 5576404192,
      "category_id": 7703517192,
      "segmentation": [],
      "area": 900.0576000000001,
      "bbox": [
        307.26976,
        545.0,
        30.001920000000002,
        30.0
      ]
    },
    {
      "id": 2165804193,
      "image_id": 5576404192,
      "category_id": 7703517192,
      "segmentation": [],
      "area": 1116.01152,
      "bbox": [
        407.2736,
        537.00032,
        31.000320000000002,
        36.0
      ]
    },
    {
      "id": 1501985193,
      "image_id": 5576404192,
      "category_id": 7703517192,
      "segmentation": [],
      "area": 863.9929597952001,
      "bbox": [
        385.27328000000006,
        554.9996799999999,
        31.999360000000003,
        27.000320000000002
      ]
    },
    {
      "id": 5428167193,
      "image_id": 5576404192,
      "category_id": 7703517192,
      "segmentation": [],
      "area": 816.0614400000001,
      "bbox": [
        550.27104,
        592.0,
        34.00256,
        24.0
      ]
    },
    {
      "id": 3063607193,
      "image_id": 5576404192,
      "category_id": 7703517192,
      "segmentation": [],
      "area": 895.3917014016001,
      "bbox": [
        579.27104,
        542.15552,
        30.001920000000002,
        29.84448
      ]
    },
    {
      "id": 6252671193,
      "image_id": 5576404192,
      "category_id": 7703517192,
      "segmentation": [],
      "area": 617.47994624,
      "bbox": [
        419.4483200000001,
        614.336,
        24.060160000000003,
        25.663999999999998
      ]
    }
  ],
  "categories": [
    {
      "id": 7703517192,
      "name": "CherryBBCH72",
      "supercategory": "cherry"
    }
  ]
}