{
  "info": {
    "description": "CherryBBCH72 Dataset - Cherry fruit images captured during fruit development stage (BBCH 72-73)",
    "version": "1.0",
    "year": 2025,
    "contributor": "search engine",
    "source": "augmented",
    "license": {
      "name": "Creative Commons Attribution 4.0 International",
      "url": "https://creativecommons.org/licenses/by/4.0/"
    }
  },
  "images": [
    {
      "id": 9076817461,
      "width": 640,
      "height": 640,
      "file_name": "IMGP8757_7.jpg",
      "size": 39947,
      "format": "JPEG",
      "url": "",
      "hash": "",
      "status": "success"
    }
  ],
  "annotations": [
    {
      "id": 8283312462,
      "image_id": 9076817461,
      "category_id": 9023841461,
      "segmentation": [],
      "area": 420.0319999999999,
      "bbox": [
        513.27136,
        185.00032000000002,
        21.001599999999996,
        20.0
      ]
    },
    {
      "id": 3295374462,
      "image_id": 9076817461,
      "category_id": 9023841461,
      "segmentation": [],
      "area": 360.0,
      "bbox": [
        526.2748799999999,
        146.99968,
        18.0,
        20.0
      ]
    },
    {
      "id": 3837751462,
      "image_id": 9076817461,
      "category_id": 9023841461,
      "segmentation": [],
      "area": 559.92832,
      "bbox": [
        511.27103999999997,
        114.0,
        19.99744,
        28.0
      ]
    },
    {
      "id": 6507852462,
      "image_id": 9076817461,
      "category_id": 9023841461,
      "segmentation": [],
      "area": 1020.06528,
      "bbox": [
        482.27072,
        107.00000000000001,
        30.001920000000002,
        34.0
      ]
    },
    {
      "id": 3545744462,
      "image_id": 9076817461,
      "category_id": 9023841461,
      "segmentation": [],
      "area": 462.00639979519997,
      "bbox": [
        464.2713600000001,
        169.00032000000004,
        22.000639999999997,
        20.99968
      ]
    },
    {
      "id": 6604169462,
      "image_id": 9076817461,
      "category_id": 9023841461,
      "segmentation": [],
      "area": 623.9500800000001,
      "bbox": [
        587.27392,
        101.0,
        23.99808,
        26.0
      ]
    },
    {
      "id": 9705484462,
      "image_id": 9076817461,
      "category_id": 9023841461,
      "segmentation": [],
      "area": 1977.9321593856002,
      "bbox": [
        493.27168,
        486.0,
        45.99808,
        43.00032
      ]
    },
    {
      "id": 4814159462,
      "image_id": 9076817461,
      "category_id": 9023841461,
      "segmentation": [],
      "area": 679.6661846016001,
      "bbox": [
        546.27232,
        443.99968,
        26.99968,
        25.17312
      ]
    },
    {
      "id": 1393844462,
      "image_id": 9076817461,
      "category_id": 9023841461,
      "segmentation": [],
      "area": 1840.0294400000002,
      "bbox": [
        551.2745600000001,
        423.00000000000006,
        40.000640000000004,
        46.0
      ]
    },
    {
      "id": 3987149462,
      "image_id": 9076817461,
      "category_id": 9023841461,
      "segmentation": [],
      "area": 1072.8841609216001,
      "bbox": [
        588.27584,
        435.00032,
        28.997120000000002,
        36.99968
      ]
    },
    {
      "id": 1815851462,
      "image_id": 9076817461,
      "category_id": 9023841461,
      "segmentation": [],
      "area": 378.02879999999993,
      "bbox": [
        609.2687999999999,
        471.99968,
        21.001599999999996,
        18.0
      ]
    },
    {
      "id": 6191034462,
      "image_id": 9076817461,
      "category_id": 9023841461,
      "segmentation": [],
      "area": 931.9208734719998,
      "bbox": [
        617.27008,
        485.0,
        22.729599999999998,
        41.000319999999995
      ]
    },
    {
      "id": 6043691462,
      "image_id": 9076817461,
      "category_id": 9023841461,
      "segmentation": [],
      "area": 418.0777238528,
      "bbox": [
        577.4438399999999,
        479.59904,
        20.04992,
        20.85184
      ]
    }
  ],
  "categories": [
    {
      "id": 9023841461,
      "name": "CherryBBCH72",
      "supercategory": "cherry"
    }
  ]
}