{
  "info": {
    "description": "CherryBBCH72 Dataset - Cherry fruit images captured during fruit development stage (BBCH 72-73)",
    "version": "1.0",
    "year": 2025,
    "contributor": "search engine",
    "source": "augmented",
    "license": {
      "name": "Creative Commons Attribution 4.0 International",
      "url": "https://creativecommons.org/licenses/by/4.0/"
    }
  },
  "images": [
    {
      "id": 9329352322,
      "width": 640,
      "height": 640,
      "file_name": "IMGP8643_21.jpg",
      "size": 41795,
      "format": "JPEG",
      "url": "",
      "hash": "",
      "status": "success"
    }
  ],
  "annotations": [
    {
      "id": 9553261322,
      "image_id": 9329352322,
      "category_id": 2900298322,
      "segmentation": [],
      "area": 339.9628791808,
      "bbox": [
        481.27039999999994,
        51.99968,
        19.99744,
        17.00032
      ]
    },
    {
      "id": 5867417322,
      "image_id": 9329352322,
      "category_id": 2900298322,
      "segmentation": [],
      "area": 419.93984081920007,
      "bbox": [
        465.27423999999996,
        25.999999999999996,
        19.99744,
        20.99968
      ]
    },
    {
      "id": 2818094322,
      "image_id": 9329352322,
      "category_id": 2900298322,
      "segmentation": [],
      "area": 951.95648,
      "bbox": [
        417.27232000000004,
        157.0,
        27.998720000000002,
        34.0
      ]
    },
    {
      "id": 8955847322,
      "image_id": 9329352322,
      "category_id": 2900298322,
      "segmentation": [],
      "area": 608.9302409216001,
      "bbox": [
        179.2736,
        271.00032000000004,
        28.997120000000002,
        20.99968
      ]
    },
    {
      "id": 6506804322,
      "image_id": 9329352322,
      "category_id": 2900298322,
      "segmentation": [],
      "area": 840.05376,
      "bbox": [
        42.268159999999995,
        304.0,
        30.001920000000002,
        28.0
      ]
    },
    {
      "id": 7380810322,
      "image_id": 9329352322,
      "category_id": 2900298322,
      "segmentation": [],
      "area": 599.9596793856001,
      "bbox": [
        14.27552,
        279.0,
        23.99808,
        25.000320000000002
      ]
    },
    {
      "id": 6968361322,
      "image_id": 9329352322,
      "category_id": 2900298322,
      "segmentation": [],
      "area": 727.96672,
      "bbox": [
        60.27072,
        207.0,
        27.998720000000002,
        26.0
      ]
    },
    {
      "id": 9656660322,
      "image_id": 9329352322,
      "category_id": 2900298322,
      "segmentation": [],
      "area": 341.7202327552,
      "bbox": [
        0.0,
        253.00032000000002,
        16.27264,
        20.99968
      ]
    },
    {
      "id": 1307122322,
      "image_id": 9329352322,
      "category_id": 2900298322,
      "segmentation": [],
      "area": 597.97504,
      "bbox": [
        555.2704,
        475.99968,
        22.99904,
        26.0
      ]
    },
    {
      "id": 1182555322,
      "image_id": 9329352322,
      "category_id": 2900298322,
      "segmentation": [],
      "area": 890.9500792832,
      "bbox": [
        524.2704000000001,
        462.0,
        32.99776,
        27.000320000000002
      ]
    },
    {
      "id": 8505182322,
      "image_id": 9329352322,
      "category_id": 2900298322,
      "segmentation": [],
      "area": 432.0742408192,
      "bbox": [
        260.27328,
        536.0,
        16.00256,
        27.000320000000002
      ]
    },
    {
      "id": 4332879322,
      "image_id": 9329352322,
      "category_id": 2900298322,
      "segmentation": [],
      "area": 484.0140799999999,
      "bbox": [
        256.26944000000003,
        573.99968,
        22.000639999999997,
        22.0
      ]
    },
    {
      "id": 1762334322,
      "image_id": 9329352322,
      "category_id": 2900298322,
      "segmentation": [],
      "area": 671.94624,
      "bbox": [
        268.27103999999997,
        584.99968,
        23.99808,
        28.0
      ]
    },
    {
      "id": 5429864322,
      "image_id": 9329352322,
      "category_id": 2900298322,
      "segmentation": [],
      "area": 399.9488,
      "bbox": [
        114.27072000000001,
        497.00032,
        19.99744,
        20.0
      ]
    },
    {
      "id": 8671000322,
      "image_id": 9329352322,
      "category_id": 2900298322,
      "segmentation": [],
      "area": 366.58176,
      "bbox": [
        0.0,
        506.99968,
        15.274239999999999,
        24.0
      ]
    }
  ],
  "categories": [
    {
      "id": 2900298322,
      "name": "CherryBBCH72",
      "supercategory": "cherry"
    }
  ]
}