{
  "info": {
    "description": "CherryBBCH72 Dataset - Cherry fruit images captured during fruit development stage (BBCH 72-73)",
    "version": "1.0",
    "year": 2025,
    "contributor": "search engine",
    "source": "augmented",
    "license": {
      "name": "Creative Commons Attribution 4.0 International",
      "url": "https://creativecommons.org/licenses/by/4.0/"
    }
  },
  "images": [
    {
      "id": 1861727241,
      "width": 640,
      "height": 640,
      "file_name": "IMGP8653_27.jpg",
      "size": 42038,
      "format": "JPEG",
      "url": "",
      "hash": "",
      "status": "success"
    }
  ],
  "annotations": [
    {
      "id": 8781122242,
      "image_id": 1861727241,
      "category_id": 3779625241,
      "segmentation": [],
      "area": 321.9061604351999,
      "bbox": [
        317.27232,
        188.99967999999998,
        17.966079999999998,
        17.91744
      ]
    },
    {
      "id": 9183845242,
      "image_id": 1861727241,
      "category_id": 3779625241,
      "segmentation": [],
      "area": 413.98272000000003,
      "bbox": [
        224.27392,
        315.0,
        22.99904,
        18.0
      ]
    },
    {
      "id": 6861413242,
      "image_id": 1861727241,
      "category_id": 3779625241,
      "segmentation": [],
      "area": 379.94496081920005,
      "bbox": [
        218.27264,
        340.00032,
        19.99744,
        18.99968
      ]
    },
    {
      "id": 9161727242,
      "image_id": 1861727241,
      "category_id": 3779625241,
      "segmentation": [],
      "area": 357.02047948799986,
      "bbox": [
        246.26847999999998,
        445.00032,
        21.001599999999996,
        16.999679999999998
      ]
    },
    {
      "id": 9391012242,
      "image_id": 1861727241,
      "category_id": 3779625241,
      "segmentation": [],
      "area": 369.662779392,
      "bbox": [
        270.27263999999997,
        421.0528,
        17.64736,
        20.947200000000002
      ]
    },
    {
      "id": 9314597242,
      "image_id": 1861727241,
      "category_id": 3779625241,
      "segmentation": [],
      "area": 360.96352051200006,
      "bbox": [
        345.27072000000004,
        411.0,
        18.9984,
        18.99968
      ]
    },
    {
      "id": 4300650242,
      "image_id": 1861727241,
      "category_id": 3779625241,
      "segmentation": [],
      "area": 575.0435192831999,
      "bbox": [
        366.27263999999997,
        452.00031999999993,
        25.002239999999997,
        22.999679999999998
      ]
    },
    {
      "id": 8065295242,
      "image_id": 1861727241,
      "category_id": 3779625241,
      "segmentation": [],
      "area": 494.0326404096,
      "bbox": [
        343.27328,
        490.0,
        26.00128,
        19.00032
      ]
    },
    {
      "id": 3200780242,
      "image_id": 1861727241,
      "category_id": 3779625241,
      "segmentation": [],
      "area": 419.93984081920007,
      "bbox": [
        231.2736,
        553.00032,
        19.99744,
        20.99968
      ]
    },
    {
      "id": 7024801242,
      "image_id": 1861727241,
      "category_id": 3779625241,
      "segmentation": [],
      "area": 303.9744,
      "bbox": [
        239.2752,
        494.99968,
        18.9984,
        16.0
      ]
    },
    {
      "id": 7015233242,
      "image_id": 1861727241,
      "category_id": 3779625241,
      "segmentation": [],
      "area": 273.3590052864,
      "bbox": [
        337.64415999999994,
        208.52128,
        20.04992,
        13.63392
      ]
    },
    {
      "id": 8548455242,
      "image_id": 1861727241,
      "category_id": 3779625241,
      "segmentation": [],
      "area": 173.6643100672,
      "bbox": [
        311.17792000000003,
        552.58176,
        12.030080000000002,
        14.435839999999999
      ]
    }
  ],
  "categories": [
    {
      "id": 3779625241,
      "name": "CherryBBCH72",
      "supercategory": "cherry"
    }
  ]
}